autohire/__init__.py
autohire/agents.py
autohire/core.py
autohire/utils.py
autohire-0.1.1.dist-info/METADATA
autohire-0.1.1.dist-info/WHEEL
autohire-0.1.1.dist-info/entry_points.txt
autohire-0.1.1.dist-info/top_level.txt
autohire-0.1.1.dist-info/RECORD
