Metadata-Version: 2.4
Name: autohire
Version: 0.1.1
Summary: AI-powered resume tailoring and job application assistant
Home-page: https://github.com/YourUsername/AutoHire_AI
Author: AutoHire Team
Author-email: your.email@example.com
Keywords: ai,resume,career,automation,llm
Classifier: Development Status :: 3 - Alpha
Classifier: Intended Audience :: Developers
Classifier: Topic :: Software Development :: Build Tools
Classifier: License :: OSI Approved :: MIT License
Classifier: Programming Language :: Python :: 3
Classifier: Programming Language :: Python :: 3.8
Classifier: Programming Language :: Python :: 3.9
Classifier: Programming Language :: Python :: 3.10
Classifier: Programming Language :: Python :: 3.11
Requires-Python: >=3.8
Requires-Dist: chainlit>=1.0.0
Requires-Dist: openai>=1.0.0
Requires-Dist: langchain>=0.1.0
Requires-Dist: langchain-openai
Requires-Dist: langchain-community
Requires-Dist: pypdf
Requires-Dist: python-dotenv
Requires-Dist: fpdf2
Requires-Dist: beautifulsoup4
Requires-Dist: python-docx
Dynamic: author
Dynamic: author-email
Dynamic: classifier
Dynamic: description
Dynamic: description-content-type
Dynamic: home-page
Dynamic: keywords
Dynamic: requires-dist
Dynamic: requires-python
Dynamic: summary
